fxp_jax/__init__.py
fxp_jax/fxp_jax.py
fxp_jax-0.2.5.dist-info/licenses/LICENSE
fxp_jax-0.2.5.dist-info/METADATA
fxp_jax-0.2.5.dist-info/WHEEL
fxp_jax-0.2.5.dist-info/top_level.txt
fxp_jax-0.2.5.dist-info/RECORD
