Metadata-Version: 2.4
Name: fxp-jax
Version: 0.2.5
Summary: Simple fixed-point solver implemented in JAX
Requires-Python: >=3.11
License-File: LICENSE
Requires-Dist: jax>=0.7.0
Requires-Dist: simple-pytree>=0.2.2
Dynamic: license-file
